grpc_service/conf/__init__.py
grpc_service/core/__init__.py
grpc_service/core/base_model.py
grpc_service/core/base_pipeline.py
grpc_service/exception/__init__.py
grpc_service/exception/base.py
grpc_service/framework/__init__.py
grpc_service/framework/inference.py
grpc_service/framework/start_model.py
grpc_service/framework/start_pipeline.py
grpc_service/framework/start_server.py
grpc_service/pb/__init__.py
grpc_service/pb/service.proto
grpc_service/pb/service_pb2.py
grpc_service/pb/service_pb2_grpc.py
grpc_service/utils/__init__.py
grpc_service/utils/authentication.py
grpc_service/utils/crop_image.py
grpc_service/utils/detection.py
grpc_service/utils/feature.py
grpc_service/utils/simple_logger.py
grpc_service/utils/utils.py
suirenshi-0.2.2.dist-info/METADATA
suirenshi-0.2.2.dist-info/WHEEL
suirenshi-0.2.2.dist-info/top_level.txt
suirenshi-0.2.2.dist-info/RECORD
